MANIFEST.in
README.rst
requirements.txt
setup.py
fetcher/__init__.py
fetcher/args.py
fetcher/commons.py
fetcher/consts.py
fetcher/exceptions.py
fetcher/fetcher.py
fetcher/version.py
untroubled_spam_fetcher.egg-info/PKG-INFO
untroubled_spam_fetcher.egg-info/SOURCES.txt
untroubled_spam_fetcher.egg-info/dependency_links.txt
untroubled_spam_fetcher.egg-info/entry_points.txt
untroubled_spam_fetcher.egg-info/requires.txt
untroubled_spam_fetcher.egg-info/top_level.txt