Metadata-Version: 1.1
Name: untroubled-spam-fetcher
Version: 0.2.1
Summary: This tool gets the Untroubled spam mails
Home-page: https://github.com/SpamScope/untroubled-spam-fetcher
Author: Fedele Mantuano
Author-email: mantuano.fedele@gmail.com
License: Apache License, Version 2.0
Keywords: mail,email,fetcher,untroubled
Platform: Linux
Classifier: License :: OSI Approved :: Apache Software License
Classifier: Intended Audience :: Developers
Classifier: Operating System :: OS Independent
Classifier: Programming Language :: Python
Classifier: Programming Language :: Python :: 3
Classifier: Programming Language :: Python :: 3.5
Classifier: Programming Language :: Python :: 3.6
